zforeach.py
zforeach-1.0.0.dist-info/METADATA
zforeach-1.0.0.dist-info/RECORD
zforeach-1.0.0.dist-info/WHEEL
zforeach-1.0.0.dist-info/top_level.txt
