Metadata-Version: 2.1
Name: zforeach
Version: 1.0.0
Summary: 对基本类型dict, list, set, tuple进行遍历, 并对遍历的数据进行操作
Home-page: https://pypi.org/
Author: zlyuan
Author-email: 1277260932@qq.com
License: GNU GENERAL PUBLIC LICENSE
Platform: all
Classifier: Environment :: Web Environment
Classifier: Intended Audience :: Developers
Classifier: Operating System :: OS Independent
Classifier: Programming Language :: Python
Classifier: Programming Language :: Python :: 3
Classifier: Programming Language :: Python :: 3.5
Classifier: Programming Language :: Python :: 3.6
